README.rst
setup.py
pfc/main.py
pfc/proxy.py
proxy_flow_control.egg-info/PKG-INFO
proxy_flow_control.egg-info/SOURCES.txt
proxy_flow_control.egg-info/dependency_links.txt
proxy_flow_control.egg-info/entry_points.txt
proxy_flow_control.egg-info/top_level.txt