Metadata-Version: 2.1
Name: proxy-flow-control
Version: 1.0.0
Summary: https://github.com/Haoke98/FlowPilot/README.md
Home-page: https://github.com/Haoke98/FlowPilot
Author: Haoke98
Author-email: ouzheng1993@gmail.com
License: MIT
Keywords: proxy flow control
Classifier: Development Status :: 5 - Production/Stable
Classifier: Environment :: Console
Classifier: Intended Audience :: Developers
Classifier: Intended Audience :: Information Technology
Classifier: Intended Audience :: Education
Classifier: Intended Audience :: Science/Research
Classifier: License :: OSI Approved :: MIT License
Classifier: Natural Language :: English
Classifier: Operating System :: OS Independent
Classifier: Topic :: Scientific/Engineering :: Visualization
Classifier: Programming Language :: Python :: 3.6
Classifier: Programming Language :: Python :: 3.7
Classifier: Programming Language :: Python :: 3.8
Requires-Python: >=3.7
